datesy/__init__.py
datesy/_helper.py
datesy/auslagerung.py
datesy/convert.py
datesy/inspect.py
datesy/matching.py
datesy/shortcuts.py
datesy/sort.py
datesy/test_iter.py
datesy/database_IO/__init__.py
datesy/database_IO/_db_helper.py
datesy/database_IO/_mysql.py
datesy/database_IO/backup.py
datesy/database_IO/inh_test.py
datesy/database_IO/sql_query.py
datesy/database_IO/test_new_db.py
datesy/file_IO/__init__.py
datesy/file_IO/csv_file.py
datesy/file_IO/file_selection.py
datesy/file_IO/json_file.py
datesy/file_IO/xls_file.py
datesy/file_IO/xml_file.py
datesy-0.9.0.dist-info/LICENSE
datesy-0.9.0.dist-info/METADATA
datesy-0.9.0.dist-info/WHEEL
datesy-0.9.0.dist-info/top_level.txt
datesy-0.9.0.dist-info/RECORD
