Metadata-Version: 2.1
Name: datesy
Version: 0.9.0
Summary: basic tools for taking care for making the intro to handling handling with python easier
Home-page: https://github.com/janluak/datesy
Author: Jan Lukas Braje
Author-email: datesy@braje.org
License: Apache 2.0
Platform: UNKNOWN
Classifier: Development Status :: 3 - Alpha
Classifier: Intended Audience :: Information Technology
Classifier: License :: OSI Approved :: Apache Software License
Classifier: Operating System :: OS Independent
Classifier: Programming Language :: Python :: 3.6
Requires-Python: >=3.6
Requires-Dist: pandas
Requires-Dist: xmltodict
Requires-Dist: openpyxl
Requires-Dist: xlrd
